realtimex_social_media_posts_tools/__init__.py
realtimex_social_media_posts_tools/cli.py
realtimex_social_media_posts_tools/content_creator/brand_guidelines_manager.py
realtimex_social_media_posts_tools/content_creator/content_creator.py
realtimex_social_media_posts_tools/content_creator/image_generator.py
realtimex_social_media_posts_tools/content_creator/platform_formatter.py
realtimex_social_media_posts_tools/content_creator/text_generator.py
realtimex_social_media_posts_tools/utils.py
realtimex_social_media_posts_tools-1.0.2.dist-info/WHEEL
realtimex_social_media_posts_tools-1.0.2.dist-info/entry_points.txt
realtimex_social_media_posts_tools-1.0.2.dist-info/METADATA
realtimex_social_media_posts_tools-1.0.2.dist-info/RECORD
