Metadata-Version: 2.3
Name: realtimex-social-media-posts-tools
Version: 1.0.2
Summary: Add your description here
Author: rta_phuongnguyen
Author-email: rta_phuongnguyen <phuongnguyen@rtanalytics.vn>
Requires-Dist: fastmcp
Requires-Dist: openai
Requires-Dist: tabulate
Requires-Dist: crawl4ai
Requires-Dist: playwright
Requires-Python: >=3.11
